{"sections":{"banner":{"type":"main-collection-banner","disabled":true,"settings":{"show_collection_description":true,"show_collection_image":false,"color_scheme":"scheme-1"}},"image_banner_TC8rfh":{"type":"image-banner","blocks":{"heading_dF9ANc":{"type":"heading","settings":{"heading":"","heading_size":"h1"}},"text_CGdHRy":{"type":"text","settings":{"text":"","text_style":"body"}},"buttons_NPRVAm":{"type":"buttons","settings":{"button_label_1":"","button_link_1":"","button_style_secondary_1":false,"button_label_2":"","button_link_2":"","button_style_secondary_2":false}}},"block_order":["heading_dF9ANc","text_CGdHRy","buttons_NPRVAm"],"disabled":true,"settings":{"image":"shopify:\/\/shop_images\/aa.png","image_overlay_opacity":0,"image_height":"medium","desktop_content_position":"bottom-left","show_text_box":true,"desktop_content_alignment":"left","color_scheme":"scheme-1","image_behavior":"none","mobile_content_alignment":"center","stack_images_on_mobile":true,"show_text_below":true}},"rich_text_hz8xHw":{"type":"rich-text","blocks":{"heading_cWYNjc":{"type":"heading","settings":{"heading":"","heading_size":"h1"}},"text_wWMHpp":{"type":"text","settings":{"text":"<p>With years of experience in interior design field, we have assisted hundreds of customers to improve their home as well as their lifestyle.<\/p>"}},"button_w899Wj":{"type":"button","settings":{"button_label":"","button_link":"","button_style_secondary":false,"button_label_2":"","button_link_2":"","button_style_secondary_2":false}}},"block_order":["heading_cWYNjc","text_wWMHpp","button_w899Wj"],"disabled":true,"settings":{"desktop_content_position":"left","content_alignment":"left","color_scheme":"","full_width":true,"padding_top":20,"padding_bottom":28}},"product-grid":{"type":"main-collection-product-grid","custom_css":[],"settings":{"products_per_page":16,"columns_desktop":4,"color_scheme":"scheme-2","image_ratio":"square","image_shape":"default","show_secondary_image":false,"show_vendor":false,"show_rating":false,"quick_add":"none","enable_filtering":false,"filter_type":"horizontal","enable_sorting":false,"columns_mobile":"2","padding_top":12,"padding_bottom":36}},"image_banner_kBFCmA":{"type":"image-banner","blocks":{"heading_rmLN7x":{"type":"heading","settings":{"heading":"","heading_size":"h1"}},"text_ATPKMb":{"type":"text","settings":{"text":"","text_style":"body"}},"buttons_qndamH":{"type":"buttons","settings":{"button_label_1":"","button_link_1":"","button_style_secondary_1":false,"button_label_2":"","button_link_2":"","button_style_secondary_2":false}}},"block_order":["heading_rmLN7x","text_ATPKMb","buttons_qndamH"],"disabled":true,"settings":{"image":"shopify:\/\/shop_images\/Section_2.png","image_overlay_opacity":0,"image_height":"medium","desktop_content_position":"middle-center","show_text_box":true,"desktop_content_alignment":"center","color_scheme":"","image_behavior":"none","mobile_content_alignment":"center","stack_images_on_mobile":true,"show_text_below":true}}},"order":["banner","image_banner_TC8rfh","rich_text_hz8xHw","product-grid","image_banner_kBFCmA"]}